pytest_embedded/__init__.py
pytest_embedded/app.py
pytest_embedded/dut.py
pytest_embedded/dut_factory.py
pytest_embedded/log.py
pytest_embedded/plugin.py
pytest_embedded/unity.py
pytest_embedded/utils.py
pytest_embedded-2.5.0.dist-info/entry_points.txt
pytest_embedded-2.5.0.dist-info/licenses/LICENSE
pytest_embedded-2.5.0.dist-info/WHEEL
pytest_embedded-2.5.0.dist-info/METADATA
pytest_embedded-2.5.0.dist-info/RECORD
